liketapi/__init__.py
liketapi/exceptions.py
liketapi/logger.py
liketapi/telegram.py
liketapi/bot/__init__.py
liketapi/bot/bot.py
liketapi/bot/methods.py
liketapi/bot/session.py
liketapi/enums/__init__.py
liketapi/enums/bot_command_scope_type.py
liketapi/enums/chat_action.py
liketapi/enums/chat_member_status.py
liketapi/enums/chat_type.py
liketapi/enums/content_type.py
liketapi/enums/dice_emoji.py
liketapi/enums/inline_query_result_type.py
liketapi/enums/input_media_type.py
liketapi/enums/mask_position_point.py
liketapi/enums/menu_button_type.py
liketapi/enums/message_entity_type.py
liketapi/enums/parse_mode.py
liketapi/enums/poll_type.py
liketapi/enums/sticker_type.py
liketapi/enums/topic_icon_color.py
liketapi/enums/update_type.py
liketapi/methods/__init__.py
liketapi/methods/add_sticker_to_set.py
liketapi/methods/answer_callback_query.py
liketapi/methods/answer_inline_query.py
liketapi/methods/answer_pre_checkout_query.py
liketapi/methods/answer_shipping_query.py
liketapi/methods/answer_web_app_query.py
liketapi/methods/approve_chat_join_request.py
liketapi/methods/ban_chat_member.py
liketapi/methods/ban_chat_sender_chat.py
liketapi/methods/base.py
liketapi/methods/close.py
liketapi/methods/close_forum_topic.py
liketapi/methods/close_general_forum_topic.py
liketapi/methods/copy_message.py
liketapi/methods/create_chat_invite_link.py
liketapi/methods/create_forum_topic.py
liketapi/methods/create_invoice_link.py
liketapi/methods/create_new_sticker_set.py
liketapi/methods/decline_chat_join_request.py
liketapi/methods/delete_chat_photo.py
liketapi/methods/delete_chat_sticker_set.py
liketapi/methods/delete_forum_topic.py
liketapi/methods/delete_message.py
liketapi/methods/delete_my_commands.py
liketapi/methods/delete_sticker_from_set.py
liketapi/methods/delete_webhook.py
liketapi/methods/edit_chat_invite_link.py
liketapi/methods/edit_forum_topic.py
liketapi/methods/edit_general_forum_topic.py
liketapi/methods/edit_message_caption.py
liketapi-1.0.dist-info/METADATA
liketapi-1.0.dist-info/WHEEL
liketapi-1.0.dist-info/RECORD
